mocca_ae/__init__.py
mocca_ae/action_items.py
mocca_ae/admin_site.py
mocca_ae/apps.py
mocca_ae/baker_recipes.py
mocca_ae/choices.py
mocca_ae/list_data.py
mocca_ae/urls.py
mocca_ae/admin/__init__.py
mocca_ae/admin/ae_followup_admin.py
mocca_ae/admin/ae_initial_admin.py
mocca_ae/admin/ae_susar_admin.py
mocca_ae/admin/ae_tmg_admin.py
mocca_ae/admin/death_report_admin.py
mocca_ae/admin/death_report_tmg_admin.py
mocca_ae/admin/death_report_tmg_second_admin.py
mocca_ae/forms/__init__.py
mocca_ae/forms/ae_followup_form.py
mocca_ae/forms/ae_initial_form.py
mocca_ae/forms/ae_susar_form.py
mocca_ae/forms/ae_tmg_form.py
mocca_ae/forms/death_report_form.py
mocca_ae/forms/death_report_tmg_form.py
mocca_ae/forms/death_report_tmg_second_form.py
mocca_ae/migrations/0001_initial.py
mocca_ae/migrations/0002_auto_20210129_0556.py
mocca_ae/migrations/0003_auto_20210225_0604.py
mocca_ae/migrations/0004_auto_20210428_0005.py
mocca_ae/migrations/0005_auto_20211209_2036.py
mocca_ae/migrations/__init__.py
mocca_ae/models/__init__.py
mocca_ae/models/ae_followup.py
mocca_ae/models/ae_initial.py
mocca_ae/models/ae_susar.py
mocca_ae/models/ae_tmg.py
mocca_ae/models/death_report.py
mocca_ae/models/death_report_tmg.py
mocca_ae/models/death_report_tmg_second.py
mocca_ae/models/managers.py
mocca_ae/models/model_mixins.py
mocca_ae/pdf_reports/__init__.py
mocca_ae/pdf_reports/ae_report.py
mocca_ae/pdf_reports/death_report.py
mocca_ae/pdf_reports/inte_pdf_report_mixin.py
mocca_ae/templates/inte_ae/bootstrap3/ae_initial_description.html
mocca_ae/templatetags/__init__.py
mocca_ae/templatetags/inte_ae_extras.py
mocca_consent/__init__.py
mocca_consent/action_items.py
mocca_consent/admin_site.py
mocca_consent/apps.py
mocca_consent/baker_recipes.py
mocca_consent/choices.py
mocca_consent/consents.py
mocca_consent/constants.py
mocca_consent/randomizers.py
mocca_consent/urls.py
mocca_consent/admin/__init__.py
mocca_consent/admin/subject_consent_admin.py
mocca_consent/admin/subject_reconsent_admin.py
mocca_edc-0.1.33.dist-info/AUTHORS.rst
mocca_edc-0.1.33.dist-info/LICENSE
mocca_edc-0.1.33.dist-info/METADATA
mocca_edc-0.1.33.dist-info/WHEEL
mocca_edc-0.1.33.dist-info/top_level.txt
mocca_edc-0.1.33.dist-info/RECORD
